aecc/__init__.py
aecc/_logging.py
aecc/_options.py
aecc/admin.py
aecc/api.py
aecc/conf.py
aecc/data.py
aecc/data_connector.py
aecc/data_print.py
aecc/data_request.py
aecc/data_uploader.py
aecc/excelfile.py
aecc/main.py
aecc/user.py
aecc/util.py
aecc-0.1.0.dist-info/LICENSE
aecc-0.1.0.dist-info/METADATA
aecc-0.1.0.dist-info/WHEEL
aecc-0.1.0.dist-info/entry_points.txt
aecc-0.1.0.dist-info/top_level.txt
aecc-0.1.0.dist-info/RECORD
