Metadata-Version: 2.1
Name: aecc
Version: 0.1.0
Home-page: https://github.com/danielmsk/aecc
Download-URL: 
Author: Daniel Minseok Kwon
Author-email: daniel.minseok.kwon@gmail.com
License: MIT
Keywords: air pollution
Classifier: Operating System :: OS Independent
Classifier: Topic :: Software Development :: Libraries
Classifier: License :: OSI Approved :: MIT License
Classifier: Programming Language :: Python :: 3.4
Classifier: Programming Language :: Python :: 3.5
Classifier: Programming Language :: Python :: 3.6
License-File: LICENSE
Requires-Dist: pandas
